__init__.py
__main__.py
itrm.py
itrm-1.4.20.dist-info/licenses/LICENSE.txt
itrm-1.4.20.dist-info/METADATA
itrm-1.4.20.dist-info/WHEEL
itrm-1.4.20.dist-info/top_level.txt
itrm-1.4.20.dist-info/RECORD
